{"features":[[{"id":113,"linha":"0.205","sentido":"IDA"}],[{"id":114,"linha":"0.205","sentido":"VOLTA"}],[{"id":115,"linha":"0.215","sentido":"IDA"}],[{"id":116,"linha":"0.215","sentido":"VOLTA"}],[{"id":123,"linha":"0.225","sentido":"IDA"}],[{"id":124,"linha":"0.225","sentido":"VOLTA"}],[{"id":125,"linha":"0.234","sentido":"IDA"}],[{"id":126,"linha":"0.234","sentido":"VOLTA"}],[{"id":739,"linha":"203.6","sentido":"IDA"}],[{"id":740,"linha":"203.6","sentido":"VOLTA"}],[{"id":743,"linha":"205.1","sentido":"IDA"}],[{"id":744,"linha":"205.1","sentido":"VOLTA"}],[{"id":751,"linha":"2201","sentido":"IDA"}],[{"id":752,"linha":"2201","sentido":"VOLTA"}],[{"id":753,"linha":"2202","sentido":"IDA"}],[{"id":754,"linha":"2202","sentido":"VOLTA"}],[{"id":755,"linha":"2203","sentido":"IDA"}],[{"id":756,"linha":"2203","sentido":"VOLTA"}],[{"id":801,"linha":"3201","sentido":"IDA"}],[{"id":802,"linha":"3201","sentido":"VOLTA"}],[{"id":807,"linha":"3204","sentido":"CIRCULAR"}],[{"id":810,"linha":"3207","sentido":"IDA"}],[{"id":811,"linha":"3207","sentido":"VOLTA"}],[{"id":812,"linha":"3208","sentido":"CIRCULAR"}],[{"id":9999,"linha":"000.0", "sentido":"sem"}]]}